__init__.py
ex.py
ex_ta1c0-0.0.1.dist-info/LICENSE
ex_ta1c0-0.0.1.dist-info/METADATA
ex_ta1c0-0.0.1.dist-info/WHEEL
ex_ta1c0-0.0.1.dist-info/top_level.txt
ex_ta1c0-0.0.1.dist-info/RECORD
